cert/__init__.py
cert/inspector.py
cert/agents/__init__.py
cert/agents/config.py
cert/agents/engine.py
cert/agents/types.py
cert/agents/integrations/__init__.py
cert/agents/integrations/autogen.py
cert/agents/integrations/crewai.py
cert/agents/integrations/langchain.py
cert/agents/metrics/__init__.py
cert/agents/metrics/base.py
cert/agents/metrics/consistency.py
cert/agents/metrics/latency.py
cert/agents/metrics/output_quality.py
cert/agents/metrics/performance.py
cert/agents/metrics/robustness.py
cert/agents/providers/__init__.py
cert/agents/providers/anthropic_provider.py
cert/agents/providers/base.py
cert/agents/providers/google_provider.py
cert/agents/providers/huggingface_provider.py
cert/agents/providers/openai_provider.py
cert/agents/providers/xai_provider.py
cert/rag/__init__.py
cert/rag/detectors.py
cert/rag/embeddings.py
cert/rag/energy.py
cert/rag/fact_extractor.py
cert/rag/nli.py
cert/rag/semantic.py
cert/rag/validation.py
cert/single_model/__init__.py
cert/single_model/consistency.py
cert/single_model/intelligent_comparator.py
cert/single_model/llm_judge.py
cert/single_model/protocols.py
cert/static/.gitkeep
cert/templates/inspector.html
cert/utilities/__init__.py
cert/utilities/cli.py
cert/utilities/compare.py
cert/utilities/runner.py
cert/utilities/types.py
cert_framework-1.1.0.dist-info/licenses/LICENSE
cert_framework-1.1.0.dist-info/METADATA
cert_framework-1.1.0.dist-info/WHEEL
cert_framework-1.1.0.dist-info/entry_points.txt
cert_framework-1.1.0.dist-info/top_level.txt
cert_framework-1.1.0.dist-info/RECORD
