Metadata-Version: 2.4
Name: cert-framework
Version: 1.1.0
Summary: CERT Framework: RAG Testing + Agentic System Assessment for LLM Applications
Home-page: https://github.com/Javihaus/cert-framework
Author: Javier Marin
Author-email: Javier Marin <info@cert-framework.com>
License: ISC
Project-URL: Homepage, https://github.com/Javihaus/cert-framework
Project-URL: Bug Tracker, https://github.com/Javihaus/cert-framework/issues
Project-URL: Documentation, https://github.com/Javihaus/cert-framework#readme
Project-URL: Source Code, https://github.com/Javihaus/cert-framework
Classifier: Development Status :: 4 - Beta
Classifier: Intended Audience :: Developers
Classifier: License :: OSI Approved :: MIT License
Classifier: Operating System :: OS Independent
Classifier: Programming Language :: Python :: 3
Classifier: Programming Language :: Python :: 3.8
Classifier: Programming Language :: Python :: 3.9
Classifier: Programming Language :: Python :: 3.10
Classifier: Programming Language :: Python :: 3.11
Classifier: Programming Language :: Python :: 3.12
Classifier: Topic :: Software Development :: Testing
Classifier: Topic :: Scientific/Engineering :: Artificial Intelligence
Classifier: Topic :: Text Processing :: Linguistic
Requires-Python: >=3.8
License-File: LICENSE
Requires-Dist: sentence-transformers<3.0.0,>=2.2.0
Requires-Dist: torch>=1.11.0
Requires-Dist: transformers>=4.30.0
Requires-Dist: numpy>=1.21.0
Requires-Dist: typing-extensions>=4.0.0
Requires-Dist: scipy>=1.7.0
Provides-Extra: dev
Requires-Dist: pytest>=7.0.0; extra == "dev"
Requires-Dist: pytest-asyncio>=0.21.0; extra == "dev"
Requires-Dist: ruff>=0.1.0; extra == "dev"
Requires-Dist: mypy>=1.0.0; extra == "dev"
Requires-Dist: datasets>=2.0.0; extra == "dev"
Requires-Dist: pandas>=1.3.0; extra == "dev"
Requires-Dist: rapidfuzz>=3.0.0; extra == "dev"
Provides-Extra: inspector
Requires-Dist: flask>=2.0.0; extra == "inspector"
Requires-Dist: jinja2>=3.0.0; extra == "inspector"
Provides-Extra: langchain
Requires-Dist: langchain>=0.1.0; extra == "langchain"
Requires-Dist: langchain-core>=0.1.0; extra == "langchain"
Provides-Extra: notebook
Requires-Dist: ipython>=7.0.0; extra == "notebook"
Requires-Dist: ipywidgets>=8.0.0; extra == "notebook"
Provides-Extra: llm-judge
Requires-Dist: anthropic>=0.18.0; extra == "llm-judge"
Provides-Extra: benchmark
Requires-Dist: anthropic>=0.25.0; extra == "benchmark"
Requires-Dist: openai>=1.0.0; extra == "benchmark"
Requires-Dist: google-generativeai>=0.3.0; extra == "benchmark"
Requires-Dist: huggingface-hub>=0.20.0; extra == "benchmark"
Requires-Dist: matplotlib>=3.5.0; extra == "benchmark"
Requires-Dist: pandas>=1.3.0; extra == "benchmark"
Requires-Dist: seaborn>=0.12.0; extra == "benchmark"
Requires-Dist: pyautogen>=0.2.0; extra == "benchmark"
Requires-Dist: crewai>=0.1.0; extra == "benchmark"
Requires-Dist: nest-asyncio>=1.5.0; extra == "benchmark"
Provides-Extra: all
Requires-Dist: flask>=2.0.0; extra == "all"
Requires-Dist: jinja2>=3.0.0; extra == "all"
Requires-Dist: langchain>=0.1.0; extra == "all"
Requires-Dist: langchain-core>=0.1.0; extra == "all"
Requires-Dist: ipython>=7.0.0; extra == "all"
Requires-Dist: ipywidgets>=8.0.0; extra == "all"
Requires-Dist: anthropic>=0.25.0; extra == "all"
Requires-Dist: openai>=1.0.0; extra == "all"
Requires-Dist: google-generativeai>=0.3.0; extra == "all"
Requires-Dist: huggingface-hub>=0.20.0; extra == "all"
Requires-Dist: matplotlib>=3.5.0; extra == "all"
Requires-Dist: pandas>=1.3.0; extra == "all"
Requires-Dist: seaborn>=0.12.0; extra == "all"
Requires-Dist: pyautogen>=0.2.0; extra == "all"
Requires-Dist: crewai>=0.1.0; extra == "all"
Requires-Dist: nest-asyncio>=1.5.0; extra == "all"
Dynamic: author
Dynamic: home-page
Dynamic: license-file
Dynamic: requires-python
